haicu_eth/__init__.py
haicu_eth/__main__.py
haicu_eth/eeprom.py
haicu_eth/format.py
haicu_eth/ftdi.py
haicu_eth/zmq.py
haicu_eth-0.9.9.dist-info/licenses/LICENSE
haicu_eth-0.9.9.dist-info/METADATA
haicu_eth-0.9.9.dist-info/WHEEL
haicu_eth-0.9.9.dist-info/entry_points.txt
haicu_eth-0.9.9.dist-info/top_level.txt
haicu_eth-0.9.9.dist-info/RECORD
