Metadata-Version: 2.4
Name: haicu_eth
Version: 0.9.9
Summary: package for HAICU experiment
Author-email: Bryerton Shaw <bryerton@triumf.ca>
Maintainer-email: Bryerton Shaw <bryerton@triumf.ca>
License: MIT License
License-File: LICENSE
Requires-Dist: simplejson
Requires-Dist: pyftdi
Provides-Extra: dev
Requires-Dist: tox; extra == "dev"
Dynamic: license-file
